Tool.py
hxftestlib/__init__.py
hxftestlib/hxflibone.py
hxftestlib-1.1.6.dist-info/LICENSE.txt
hxftestlib-1.1.6.dist-info/METADATA
hxftestlib-1.1.6.dist-info/WHEEL
hxftestlib-1.1.6.dist-info/top_level.txt
hxftestlib-1.1.6.dist-info/RECORD
