Metadata-Version: 2.1
Name: hxftestlib
Version: 1.1.6
Summary: this is a baqi lib2
Home-page: https://github.com/SO2Family/Python_code
Author: hxf
Author-email: SO2@sina.com
License: MIT
Platform: UNKNOWN
